{
  "booster": null,
  "name": "Duel Decks: Speed vs. Cunning",
  "code": "DDN",
  "totalSetSize": 82,
  "cards": [
    {
      "name": "Act of Treason",
      "uuid": "4589eb1b-32f8-5c6d-9488-bc439ae70c39",
      "cmc": 3,
      "rarity": "common",
      "color": {
        "colors": [
          "R"
        ],
        "colorIdentity": [
          "R"
        ]
      },
      "type": {
        "types": [
          "Sorcery"
        ],
        "subtypes": [],
        "supertypes": []
      }
    },
    {
      "name": "Aquamorph Entity",
      "uuid": "1c5de907-1512-5631-95dd-a43a5431abe9",
      "cmc": 4,
      "rarity": "common",
      "color": {
        "colors": [
          "U"
        ],
        "colorIdentity": [
          "U"
        ]
      },
      "type": {
        "types": [
          "Creature"
        ],
        "subtypes": [
          "Shapeshifter"
        ],
        "supertypes": []
      }
    },
    {
      "name": "Arc Trail",
      "uuid": "4256c944-2309-54c7-83c0-97900a289047",
      "cmc": 2,
      "rarity": "uncommon",
      "color": {
        "colors": [
          "R"
        ],
        "colorIdentity": [
          "R"
        ]
      },
      "type": {
        "types": [
          "Sorcery"
        ],
        "subtypes": [],
        "supertypes": []
      }
    },
    {
      "name": "Arcanis the Omnipotent",
      "uuid": "6050088d-ac4c-5dcd-aea5-d8b3c9dfc4df",
      "cmc": 6,
      "rarity": "mythic",
      "color": {
        "colors": [
          "U"
        ],
        "colorIdentity": [
          "U"
        ]
      },
      "type": {
        "types": [
          "Creature"
        ],
        "subtypes": [
          "Wizard"
        ],
        "supertypes": [
          "Legendary"
        ]
      }
    },
    {
      "name": "Arrow Volley Trap",
      "uuid": "a379130e-07d7-5fbd-b17f-86ef882097be",
      "cmc": 5,
      "rarity": "uncommon",
      "color": {
        "colors": [
          "W"
        ],
        "colorIdentity": [
          "W"
        ]
      },
      "type": {
        "types": [
          "Instant"
        ],
        "subtypes": [
          "Trap"
        ],
        "supertypes": []
      }
    },
    {
      "name": "Banefire",
      "uuid": "002f0f83-16b1-5f96-a704-fdb65b5936e8",
      "cmc": 1,
      "rarity": "rare",
      "color": {
        "colors": [
          "R"
        ],
        "colorIdentity": [
          "R"
        ]
      },
      "type": {
        "types": [
          "Sorcery"
        ],
        "subtypes": [],
        "supertypes": []
      }
    },
    {
      "name": "Beetleback Chief",
      "uuid": "68976f26-20e4-5930-a74e-03874c2fd05b",
      "cmc": 4,
      "rarity": "uncommon",
      "color": {
        "colors": [
          "R"
        ],
        "colorIdentity": [
          "R"
        ]
      },
      "type": {
        "types": [
          "Creature"
        ],
        "subtypes": [
          "Goblin",
          "Warrior"
        ],
        "supertypes": []
      }
    },
    {
      "name": "Bone Splinters",
      "uuid": "e8bd3fea-40da-59ce-9fda-1f6e55b9379b",
      "cmc": 1,
      "rarity": "common",
      "color": {
        "colors": [
          "B"
        ],
        "colorIdentity": [
          "B"
        ]
      },
      "type": {
        "types": [
          "Sorcery"
        ],
        "subtypes": [],
        "supertypes": []
      }
    },
    {
      "name": "Coral Trickster",
      "uuid": "9ef03d0b-6cd1-53a7-9722-1624ec22f7f5",
      "cmc": 2,
      "rarity": "common",
      "color": {
        "colors": [
          "U"
        ],
        "colorIdentity": [
          "U"
        ]
      },
      "type": {
        "types": [
          "Creature"
        ],
        "subtypes": [
          "Merfolk",
          "Rogue"
        ],
        "supertypes": []
      }
    },
    {
      "name": "Dauntless Onslaught",
      "uuid": "b8baa76c-f45a-5c95-a853-afcf7874dea0",
      "cmc": 3,
      "rarity": "uncommon",
      "color": {
        "colors": [
          "W"
        ],
        "colorIdentity": [
          "W"
        ]
      },
      "type": {
        "types": [
          "Instant"
        ],
        "subtypes": [],
        "supertypes": []
      }
    },
    {
      "name": "Dregscape Zombie",
      "uuid": "529ee834-6a8c-5d93-81b3-493dbd0e3d30",
      "cmc": 2,
      "rarity": "common",
      "color": {
        "colors": [
          "B"
        ],
        "colorIdentity": [
          "B"
        ]
      },
      "type": {
        "types": [
          "Creature"
        ],
        "subtypes": [
          "Zombie"
        ],
        "supertypes": []
      }
    },
    {
      "name": "Echo Tracer",
      "uuid": "4320ed43-b760-56d8-a3f8-921c3720893a",
      "cmc": 3,
      "rarity": "common",
      "color": {
        "colors": [
          "U"
        ],
        "colorIdentity": [
          "U"
        ]
      },
      "type": {
        "types": [
          "Creature"
        ],
        "subtypes": [
          "Human",
          "Wizard"
        ],
        "supertypes": []
      }
    },
    {
      "name": "Evolving Wilds",
      "uuid": "98909c3b-613a-5c2e-85e2-03124ca84e3c",
      "cmc": 0,
      "rarity": "common",
      "color": {
        "colors": [],
        "colorIdentity": []
      },
      "type": {
        "types": [
          "Land"
        ],
        "subtypes": [],
        "supertypes": []
      }
    },
    {
      "name": "Faerie Impostor",
      "uuid": "79c7f628-847f-5864-8220-2cf666e7fed6",
      "cmc": 1,
      "rarity": "uncommon",
      "color": {
        "colors": [
          "U"
        ],
        "colorIdentity": [
          "U"
        ]
      },
      "type": {
        "types": [
          "Creature"
        ],
        "subtypes": [
          "Faerie",
          "Rogue"
        ],
        "supertypes": []
      }
    },
    {
      "name": "Faerie Invaders",
      "uuid": "3a862762-2078-55d3-bb52-3e0d3216f79e",
      "cmc": 5,
      "rarity": "common",
      "color": {
        "colors": [
          "U"
        ],
        "colorIdentity": [
          "U"
        ]
      },
      "type": {
        "types": [
          "Creature"
        ],
        "subtypes": [
          "Faerie",
          "Rogue"
        ],
        "supertypes": []
      }
    },
    {
      "name": "Fathom Seer",
      "uuid": "afd759f0-4331-5e06-9c30-72ac34083760",
      "cmc": 2,
      "rarity": "common",
      "color": {
        "colors": [
          "U"
        ],
        "colorIdentity": [
          "U"
        ]
      },
      "type": {
        "types": [
          "Creature"
        ],
        "subtypes": [
          "Illusion"
        ],
        "supertypes": []
      }
    },
    {
      "name": "Fiery Fall",
      "uuid": "133ca4d9-bfc5-5ccd-800f-8e2395db1ec5",
      "cmc": 6,
      "rarity": "common",
      "color": {
        "colors": [
          "R"
        ],
        "colorIdentity": [
          "R"
        ]
      },
      "type": {
        "types": [
          "Instant"
        ],
        "subtypes": [],
        "supertypes": []
      }
    },
    {
      "name": "Flame-Kin Zealot",
      "uuid": "e3b106a2-4793-5ce4-aa12-bf5ea55ff789",
      "cmc": 4,
      "rarity": "uncommon",
      "color": {
        "colors": [
          "R",
          "W"
        ],
        "colorIdentity": [
          "R",
          "W"
        ]
      },
      "type": {
        "types": [
          "Creature"
        ],
        "subtypes": [
          "Elemental",
          "Berserker"
        ],
        "supertypes": []
      }
    },
    {
      "name": "Fleeting Distraction",
      "uuid": "bbb8750e-e529-5021-a8f4-8c83c5bea8aa",
      "cmc": 1,
      "rarity": "common",
      "color": {
        "colors": [
          "U"
        ],
        "colorIdentity": [
          "U"
        ]
      },
      "type": {
        "types": [
          "Instant"
        ],
        "subtypes": [],
        "supertypes": []
      }
    },
    {
      "name": "Fleshbag Marauder",
      "uuid": "99d6d941-b159-5cb9-a988-937633e45015",
      "cmc": 3,
      "rarity": "uncommon",
      "color": {
        "colors": [
          "B"
        ],
        "colorIdentity": [
          "B"
        ]
      },
      "type": {
        "types": [
          "Creature"
        ],
        "subtypes": [
          "Zombie",
          "Warrior"
        ],
        "supertypes": []
      }
    },
    {
      "name": "Frenzied Goblin",
      "uuid": "0d28c761-0c91-51c2-b20d-1942e91009a2",
      "cmc": 1,
      "rarity": "uncommon",
      "color": {
        "colors": [
          "R"
        ],
        "colorIdentity": [
          "R"
        ]
      },
      "type": {
        "types": [
          "Creature"
        ],
        "subtypes": [
          "Goblin",
          "Berserker"
        ],
        "supertypes": []
      }
    },
    {
      "name": "Fury of the Horde",
      "uuid": "c443c3d5-94b2-5f4f-bf9e-9f8d83f883d5",
      "cmc": 7,
      "rarity": "rare",
      "color": {
        "colors": [
          "R"
        ],
        "colorIdentity": [
          "R"
        ]
      },
      "type": {
        "types": [
          "Sorcery"
        ],
        "subtypes": [],
        "supertypes": []
      }
    },
    {
      "name": "Ghitu Encampment",
      "uuid": "2e6b1d80-5100-554d-b8ea-04ac041265fc",
      "cmc": 0,
      "rarity": "uncommon",
      "color": {
        "colors": [],
        "colorIdentity": [
          "R"
        ]
      },
      "type": {
        "types": [
          "Land"
        ],
        "subtypes": [],
        "supertypes": []
      }
    },
    {
      "name": "Goblin Bombardment",
      "uuid": "f5a776ec-47a9-5d27-803a-43cf8350953f",
      "cmc": 2,
      "rarity": "uncommon",
      "color": {
        "colors": [
          "R"
        ],
        "colorIdentity": [
          "R"
        ]
      },
      "type": {
        "types": [
          "Enchantment"
        ],
        "subtypes": [],
        "supertypes": []
      }
    },
    {
      "name": "Goblin Deathraiders",
      "uuid": "dc3ab67f-db0f-521e-a7ab-be6155748ffd",
      "cmc": 2,
      "rarity": "common",
      "color": {
        "colors": [
          "B",
          "R"
        ],
        "colorIdentity": [
          "B",
          "R"
        ]
      },
      "type": {
        "types": [
          "Creature"
        ],
        "subtypes": [
          "Goblin",
          "Warrior"
        ],
        "supertypes": []
      }
    },
    {
      "name": "Goblin Warchief",
      "uuid": "24776a94-92c8-5aa7-8d9d-ed47d29caacb",
      "cmc": 3,
      "rarity": "uncommon",
      "color": {
        "colors": [
          "R"
        ],
        "colorIdentity": [
          "R"
        ]
      },
      "type": {
        "types": [
          "Creature"
        ],
        "subtypes": [
          "Goblin",
          "Warrior"
        ],
        "supertypes": []
      }
    },
    {
      "name": "Hell's Thunder",
      "uuid": "fd0d7ec7-856a-5484-a470-8e2208b2200a",
      "cmc": 3,
      "rarity": "rare",
      "color": {
        "colors": [
          "R"
        ],
        "colorIdentity": [
          "R"
        ]
      },
      "type": {
        "types": [
          "Creature"
        ],
        "subtypes": [
          "Elemental"
        ],
        "supertypes": []
      }
    },
    {
      "name": "Hellraiser Goblin",
      "uuid": "97c1011c-f66b-54d2-bf5a-0c131064d697",
      "cmc": 3,
      "rarity": "uncommon",
      "color": {
        "colors": [
          "R"
        ],
        "colorIdentity": [
          "R"
        ]
      },
      "type": {
        "types": [
          "Creature"
        ],
        "subtypes": [
          "Goblin",
          "Berserker"
        ],
        "supertypes": []
      }
    },
    {
      "name": "Hold the Line",
      "uuid": "5738453a-db70-5010-9716-c1cdb46c8d7f",
      "cmc": 3,
      "rarity": "rare",
      "color": {
        "colors": [
          "W"
        ],
        "colorIdentity": [
          "W"
        ]
      },
      "type": {
        "types": [
          "Instant"
        ],
        "subtypes": [],
        "supertypes": []
      }
    },
    {
      "name": "Hussar Patrol",
      "uuid": "80283d99-cf32-5a0c-b782-28786583f924",
      "cmc": 4,
      "rarity": "common",
      "color": {
        "colors": [
          "U",
          "W"
        ],
        "colorIdentity": [
          "U",
          "W"
        ]
      },
      "type": {
        "types": [
          "Creature"
        ],
        "subtypes": [
          "Human",
          "Knight"
        ],
        "supertypes": []
      }
    },
    {
      "name": "Impulse",
      "uuid": "080f863e-2f2c-5c84-b44a-76b74e563d99",
      "cmc": 2,
      "rarity": "common",
      "color": {
        "colors": [
          "U"
        ],
        "colorIdentity": [
          "U"
        ]
      },
      "type": {
        "types": [
          "Instant"
        ],
        "subtypes": [],
        "supertypes": []
      }
    },
    {
      "name": "Infantry Veteran",
      "uuid": "a2bd113d-2599-585c-a4b4-d0ba35c30ddc",
      "cmc": 1,
      "rarity": "common",
      "color": {
        "colors": [
          "W"
        ],
        "colorIdentity": [
          "W"
        ]
      },
      "type": {
        "types": [
          "Creature"
        ],
        "subtypes": [
          "Human",
          "Soldier"
        ],
        "supertypes": []
      }
    },
    {
      "name": "Inferno Trap",
      "uuid": "0496d405-368b-5c4d-b53f-000a8b7a390e",
      "cmc": 4,
      "rarity": "uncommon",
      "color": {
        "colors": [
          "R"
        ],
        "colorIdentity": [
          "R"
        ]
      },
      "type": {
        "types": [
          "Instant"
        ],
        "subtypes": [
          "Trap"
        ],
        "supertypes": []
      }
    },
    {
      "name": "Island",
      "uuid": "9a1bca37-2f75-55be-b6d4-9a2e5cb57394",
      "cmc": 0,
      "rarity": "common",
      "color": {
        "colors": [],
        "colorIdentity": [
          "U"
        ]
      },
      "type": {
        "types": [
          "Land"
        ],
        "subtypes": [
          "Island"
        ],
        "supertypes": [
          "Basic"
        ]
      }
    },
    {
      "name": "Island",
      "uuid": "3db8fe48-9671-5d0a-9d44-31dbcf572812",
      "cmc": 0,
      "rarity": "common",
      "color": {
        "colors": [],
        "colorIdentity": [
          "U"
        ]
      },
      "type": {
        "types": [
          "Land"
        ],
        "subtypes": [
          "Island"
        ],
        "supertypes": [
          "Basic"
        ]
      }
    },
    {
      "name": "Island",
      "uuid": "2d6ceb62-2481-5656-a9dc-5198b328d9b4",
      "cmc": 0,
      "rarity": "common",
      "color": {
        "colors": [],
        "colorIdentity": [
          "U"
        ]
      },
      "type": {
        "types": [
          "Land"
        ],
        "subtypes": [
          "Island"
        ],
        "supertypes": [
          "Basic"
        ]
      }
    },
    {
      "name": "Jeskai Elder",
      "uuid": "4706d596-2d9a-5f83-bd69-59af85e16670",
      "cmc": 2,
      "rarity": "uncommon",
      "color": {
        "colors": [
          "U"
        ],
        "colorIdentity": [
          "U"
        ]
      },
      "type": {
        "types": [
          "Creature"
        ],
        "subtypes": [
          "Human",
          "Monk"
        ],
        "supertypes": []
      }
    },
    {
      "name": "Kathari Bomber",
      "uuid": "bab0f762-cc90-5994-8cc9-c8f71dfa1ec7",
      "cmc": 3,
      "rarity": "common",
      "color": {
        "colors": [
          "B",
          "R"
        ],
        "colorIdentity": [
          "B",
          "R"
        ]
      },
      "type": {
        "types": [
          "Creature"
        ],
        "subtypes": [
          "Bird",
          "Shaman"
        ],
        "supertypes": []
      }
    },
    {
      "name": "Kor Hookmaster",
      "uuid": "84fac300-2ba2-57f5-a76e-6a2ee636fead",
      "cmc": 3,
      "rarity": "common",
      "color": {
        "colors": [
          "W"
        ],
        "colorIdentity": [
          "W"
        ]
      },
      "type": {
        "types": [
          "Creature"
        ],
        "subtypes": [
          "Kor",
          "Soldier"
        ],
        "supertypes": []
      }
    },
    {
      "name": "Krenko's Command",
      "uuid": "a933948c-85bc-5b77-ab03-7a932e2a5463",
      "cmc": 2,
      "rarity": "common",
      "color": {
        "colors": [
          "R"
        ],
        "colorIdentity": [
          "R"
        ]
      },
      "type": {
        "types": [
          "Sorcery"
        ],
        "subtypes": [],
        "supertypes": []
      }
    },
    {
      "name": "Krenko, Mob Boss",
      "uuid": "f942e6c5-f222-56e1-82de-109b0408d1a1",
      "cmc": 4,
      "rarity": "rare",
      "color": {
        "colors": [
          "R"
        ],
        "colorIdentity": [
          "R"
        ]
      },
      "type": {
        "types": [
          "Creature"
        ],
        "subtypes": [
          "Goblin",
          "Warrior"
        ],
        "supertypes": [
          "Legendary"
        ]
      }
    },
    {
      "name": "Leonin Snarecaster",
      "uuid": "c4e7bc15-4532-5ddd-811e-45014b86374f",
      "cmc": 2,
      "rarity": "common",
      "color": {
        "colors": [
          "W"
        ],
        "colorIdentity": [
          "W"
        ]
      },
      "type": {
        "types": [
          "Creature"
        ],
        "subtypes": [
          "Cat",
          "Soldier"
        ],
        "supertypes": []
      }
    },
    {
      "name": "Lightning Angel",
      "uuid": "6254cb15-a313-59ae-ac53-296cd1a43c77",
      "cmc": 4,
      "rarity": "rare",
      "color": {
        "colors": [
          "R",
          "U",
          "W"
        ],
        "colorIdentity": [
          "R",
          "U",
          "W"
        ]
      },
      "type": {
        "types": [
          "Creature"
        ],
        "subtypes": [
          "Angel"
        ],
        "supertypes": []
      }
    },
    {
      "name": "Lightning Helix",
      "uuid": "df9e1afd-5ecf-59b4-8948-9f50f96009d8",
      "cmc": 2,
      "rarity": "uncommon",
      "color": {
        "colors": [
          "R",
          "W"
        ],
        "colorIdentity": [
          "R",
          "W"
        ]
      },
      "type": {
        "types": [
          "Instant"
        ],
        "subtypes": [],
        "supertypes": []
      }
    },
    {
      "name": "Lone Missionary",
      "uuid": "dd272a89-d4aa-5391-9cc3-a520d4102630",
      "cmc": 2,
      "rarity": "common",
      "color": {
        "colors": [
          "W"
        ],
        "colorIdentity": [
          "W"
        ]
      },
      "type": {
        "types": [
          "Creature"
        ],
        "subtypes": [
          "Kor",
          "Monk"
        ],
        "supertypes": []
      }
    },
    {
      "name": "Mana Leak",
      "uuid": "32e7ac24-f38c-5a34-902a-db2c1fe65ad0",
      "cmc": 2,
      "rarity": "common",
      "color": {
        "colors": [
          "U"
        ],
        "colorIdentity": [
          "U"
        ]
      },
      "type": {
        "types": [
          "Instant"
        ],
        "subtypes": [],
        "supertypes": []
      }
    },
    {
      "name": "Mardu Heart-Piercer",
      "uuid": "58f433c8-4d6b-5b53-9d0f-484a30d34e6d",
      "cmc": 4,
      "rarity": "uncommon",
      "color": {
        "colors": [
          "R"
        ],
        "colorIdentity": [
          "R"
        ]
      },
      "type": {
        "types": [
          "Creature"
        ],
        "subtypes": [
          "Human",
          "Archer"
        ],
        "supertypes": []
      }
    },
    {
      "name": "Master Decoy",
      "uuid": "b58ac78b-ca7c-57a6-9165-4a7444550d15",
      "cmc": 2,
      "rarity": "common",
      "color": {
        "colors": [
          "W"
        ],
        "colorIdentity": [
          "W"
        ]
      },
      "type": {
        "types": [
          "Creature"
        ],
        "subtypes": [
          "Human",
          "Soldier"
        ],
        "supertypes": []
      }
    },
    {
      "name": "Mountain",
      "uuid": "28e2d1f8-8199-5c17-b096-c16e2e271fb7",
      "cmc": 0,
      "rarity": "common",
      "color": {
        "colors": [],
        "colorIdentity": [
          "R"
        ]
      },
      "type": {
        "types": [
          "Land"
        ],
        "subtypes": [
          "Mountain"
        ],
        "supertypes": [
          "Basic"
        ]
      }
    },
    {
      "name": "Mountain",
      "uuid": "cd211816-85de-5d46-ba02-c3bb12429dcc",
      "cmc": 0,
      "rarity": "common",
      "color": {
        "colors": [],
        "colorIdentity": [
          "R"
        ]
      },
      "type": {
        "types": [
          "Land"
        ],
        "subtypes": [
          "Mountain"
        ],
        "supertypes": [
          "Basic"
        ]
      }
    },
    {
      "name": "Mountain",
      "uuid": "2253d4f8-0f9a-52db-ae0c-0c8298dcf936",
      "cmc": 0,
      "rarity": "common",
      "color": {
        "colors": [],
        "colorIdentity": [
          "R"
        ]
      },
      "type": {
        "types": [
          "Land"
        ],
        "subtypes": [
          "Mountain"
        ],
        "supertypes": [
          "Basic"
        ]
      }
    },
    {
      "name": "Mountain",
      "uuid": "193494f2-d259-5963-a201-737db341df17",
      "cmc": 0,
      "rarity": "common",
      "color": {
        "colors": [],
        "colorIdentity": [
          "R"
        ]
      },
      "type": {
        "types": [
          "Land"
        ],
        "subtypes": [
          "Mountain"
        ],
        "supertypes": [
          "Basic"
        ]
      }
    },
    {
      "name": "Mystic Monastery",
      "uuid": "c6ae0c4f-be3d-5d73-9020-93c32f15ff36",
      "cmc": 0,
      "rarity": "uncommon",
      "color": {
        "colors": [],
        "colorIdentity": [
          "R",
          "U",
          "W"
        ]
      },
      "type": {
        "types": [
          "Land"
        ],
        "subtypes": [],
        "supertypes": []
      }
    },
    {
      "name": "Nomad Outpost",
      "uuid": "c213e706-ead2-529f-bae4-e7549afd58a0",
      "cmc": 0,
      "rarity": "uncommon",
      "color": {
        "colors": [],
        "colorIdentity": [
          "B",
          "R",
          "W"
        ]
      },
      "type": {
        "types": [
          "Land"
        ],
        "subtypes": [],
        "supertypes": []
      }
    },
    {
      "name": "Ogre Battledriver",
      "uuid": "6cecd401-5c71-5f3f-ad81-df5427aabd6a",
      "cmc": 4,
      "rarity": "rare",
      "color": {
        "colors": [
          "R"
        ],
        "colorIdentity": [
          "R"
        ]
      },
      "type": {
        "types": [
          "Creature"
        ],
        "subtypes": [
          "Ogre",
          "Warrior"
        ],
        "supertypes": []
      }
    },
    {
      "name": "Oni of Wild Places",
      "uuid": "a04745c3-cab6-5af5-bfd3-50f23a12db91",
      "cmc": 6,
      "rarity": "uncommon",
      "color": {
        "colors": [
          "R"
        ],
        "colorIdentity": [
          "R"
        ]
      },
      "type": {
        "types": [
          "Creature"
        ],
        "subtypes": [
          "Demon",
          "Spirit"
        ],
        "supertypes": []
      }
    },
    {
      "name": "Orcish Cannonade",
      "uuid": "804686b9-a602-51db-85e6-d4ded8a62a9a",
      "cmc": 3,
      "rarity": "common",
      "color": {
        "colors": [
          "R"
        ],
        "colorIdentity": [
          "R"
        ]
      },
      "type": {
        "types": [
          "Instant"
        ],
        "subtypes": [],
        "supertypes": []
      }
    },
    {
      "name": "Plains",
      "uuid": "d9f930a3-37bc-5613-acf8-449f42c23006",
      "cmc": 0,
      "rarity": "common",
      "color": {
        "colors": [],
        "colorIdentity": [
          "W"
        ]
      },
      "type": {
        "types": [
          "Land"
        ],
        "subtypes": [
          "Plains"
        ],
        "supertypes": [
          "Basic"
        ]
      }
    },
    {
      "name": "Plains",
      "uuid": "0f058ac7-a1bf-53e7-a253-ad8367e74503",
      "cmc": 0,
      "rarity": "common",
      "color": {
        "colors": [],
        "colorIdentity": [
          "W"
        ]
      },
      "type": {
        "types": [
          "Land"
        ],
        "subtypes": [
          "Plains"
        ],
        "supertypes": [
          "Basic"
        ]
      }
    },
    {
      "name": "Plains",
      "uuid": "e835b7cb-9221-52a3-bbdb-a7023ea73e55",
      "cmc": 0,
      "rarity": "common",
      "color": {
        "colors": [],
        "colorIdentity": [
          "W"
        ]
      },
      "type": {
        "types": [
          "Land"
        ],
        "subtypes": [
          "Plains"
        ],
        "supertypes": [
          "Basic"
        ]
      }
    },
    {
      "name": "Plains",
      "uuid": "e9bddeb8-166d-527b-87eb-8086dfa7f499",
      "cmc": 0,
      "rarity": "common",
      "color": {
        "colors": [],
        "colorIdentity": [
          "W"
        ]
      },
      "type": {
        "types": [
          "Land"
        ],
        "subtypes": [
          "Plains"
        ],
        "supertypes": [
          "Basic"
        ]
      }
    },
    {
      "name": "Reckless Abandon",
      "uuid": "60e593dc-d4ea-5eba-aef9-d5241b13e2b0",
      "cmc": 1,
      "rarity": "common",
      "color": {
        "colors": [
          "R"
        ],
        "colorIdentity": [
          "R"
        ]
      },
      "type": {
        "types": [
          "Sorcery"
        ],
        "subtypes": [],
        "supertypes": []
      }
    },
    {
      "name": "Repeal",
      "uuid": "4a9abe7a-b139-5f57-a66a-b034956ce216",
      "cmc": 1,
      "rarity": "common",
      "color": {
        "colors": [
          "U"
        ],
        "colorIdentity": [
          "U"
        ]
      },
      "type": {
        "types": [
          "Instant"
        ],
        "subtypes": [],
        "supertypes": []
      }
    },
    {
      "name": "Scourge Devil",
      "uuid": "133cd757-5429-5e79-913a-ebe6a6f4a30e",
      "cmc": 5,
      "rarity": "uncommon",
      "color": {
        "colors": [
          "R"
        ],
        "colorIdentity": [
          "R"
        ]
      },
      "type": {
        "types": [
          "Creature"
        ],
        "subtypes": [
          "Devil"
        ],
        "supertypes": []
      }
    },
    {
      "name": "Shambling Remains",
      "uuid": "0e6c9685-87fb-529b-961f-28b032dcc7ed",
      "cmc": 3,
      "rarity": "uncommon",
      "color": {
        "colors": [
          "B",
          "R"
        ],
        "colorIdentity": [
          "B",
          "R"
        ]
      },
      "type": {
        "types": [
          "Creature"
        ],
        "subtypes": [
          "Zombie",
          "Horror"
        ],
        "supertypes": []
      }
    },
    {
      "name": "Shock",
      "uuid": "e6571a94-247f-5e9a-baa9-f3d163786480",
      "cmc": 1,
      "rarity": "common",
      "color": {
        "colors": [
          "R"
        ],
        "colorIdentity": [
          "R"
        ]
      },
      "type": {
        "types": [
          "Instant"
        ],
        "subtypes": [],
        "supertypes": []
      }
    },
    {
      "name": "Sparkmage Apprentice",
      "uuid": "696aa3ba-c622-520b-945a-deeee8af7e49",
      "cmc": 2,
      "rarity": "common",
      "color": {
        "colors": [
          "R"
        ],
        "colorIdentity": [
          "R"
        ]
      },
      "type": {
        "types": [
          "Creature"
        ],
        "subtypes": [
          "Human",
          "Wizard"
        ],
        "supertypes": []
      }
    },
    {
      "name": "Sphinx of Uthuun",
      "uuid": "343e7806-5a3a-5a53-9495-c6156f3f7d5e",
      "cmc": 7,
      "rarity": "rare",
      "color": {
        "colors": [
          "U"
        ],
        "colorIdentity": [
          "U"
        ]
      },
      "type": {
        "types": [
          "Creature"
        ],
        "subtypes": [
          "Sphinx"
        ],
        "supertypes": []
      }
    },
    {
      "name": "Stave Off",
      "uuid": "630405aa-679a-59ea-aa06-93499b91115b",
      "cmc": 1,
      "rarity": "common",
      "color": {
        "colors": [
          "W"
        ],
        "colorIdentity": [
          "W"
        ]
      },
      "type": {
        "types": [
          "Instant"
        ],
        "subtypes": [],
        "supertypes": []
      }
    },
    {
      "name": "Steam Augury",
      "uuid": "be939c6f-923b-579d-af03-ee1708a8738b",
      "cmc": 4,
      "rarity": "rare",
      "color": {
        "colors": [
          "R",
          "U"
        ],
        "colorIdentity": [
          "R",
          "U"
        ]
      },
      "type": {
        "types": [
          "Instant"
        ],
        "subtypes": [],
        "supertypes": []
      }
    },
    {
      "name": "Stonecloaker",
      "uuid": "2c6aabd7-432a-5432-aded-1d2297446447",
      "cmc": 3,
      "rarity": "uncommon",
      "color": {
        "colors": [
          "W"
        ],
        "colorIdentity": [
          "W"
        ]
      },
      "type": {
        "types": [
          "Creature"
        ],
        "subtypes": [
          "Gargoyle"
        ],
        "supertypes": []
      }
    },
    {
      "name": "Swamp",
      "uuid": "4ffc1867-a139-5aa5-a8bb-5aadf8fdf532",
      "cmc": 0,
      "rarity": "common",
      "color": {
        "colors": [],
        "colorIdentity": [
          "B"
        ]
      },
      "type": {
        "types": [
          "Land"
        ],
        "subtypes": [
          "Swamp"
        ],
        "supertypes": [
          "Basic"
        ]
      }
    },
    {
      "name": "Swamp",
      "uuid": "16b343ea-cd31-574d-b8c9-79d97304bfba",
      "cmc": 0,
      "rarity": "common",
      "color": {
        "colors": [],
        "colorIdentity": [
          "B"
        ]
      },
      "type": {
        "types": [
          "Land"
        ],
        "subtypes": [
          "Swamp"
        ],
        "supertypes": [
          "Basic"
        ]
      }
    },
    {
      "name": "Swamp",
      "uuid": "fb2def69-0fde-5b61-ba14-cf783acdbbf6",
      "cmc": 0,
      "rarity": "common",
      "color": {
        "colors": [],
        "colorIdentity": [
          "B"
        ]
      },
      "type": {
        "types": [
          "Land"
        ],
        "subtypes": [
          "Swamp"
        ],
        "supertypes": [
          "Basic"
        ]
      }
    },
    {
      "name": "Swift Justice",
      "uuid": "ec9e8daa-0499-5739-a26b-b397e440bfdd",
      "cmc": 1,
      "rarity": "common",
      "color": {
        "colors": [
          "W"
        ],
        "colorIdentity": [
          "W"
        ]
      },
      "type": {
        "types": [
          "Instant"
        ],
        "subtypes": [],
        "supertypes": []
      }
    },
    {
      "name": "Terramorphic Expanse",
      "uuid": "a6b6e549-5add-52cf-b2fd-25705fc93350",
      "cmc": 0,
      "rarity": "common",
      "color": {
        "colors": [],
        "colorIdentity": []
      },
      "type": {
        "types": [
          "Land"
        ],
        "subtypes": [],
        "supertypes": []
      }
    },
    {
      "name": "Thousand Winds",
      "uuid": "d4ccec17-02d8-5f7e-bb6c-14d8330d493d",
      "cmc": 6,
      "rarity": "rare",
      "color": {
        "colors": [
          "U"
        ],
        "colorIdentity": [
          "U"
        ]
      },
      "type": {
        "types": [
          "Creature"
        ],
        "subtypes": [
          "Elemental"
        ],
        "supertypes": []
      }
    },
    {
      "name": "Traumatic Visions",
      "uuid": "60002d31-3e7d-54a7-ab3b-7d5d67c0ed3d",
      "cmc": 5,
      "rarity": "common",
      "color": {
        "colors": [
          "U"
        ],
        "colorIdentity": [
          "U"
        ]
      },
      "type": {
        "types": [
          "Instant"
        ],
        "subtypes": [],
        "supertypes": []
      }
    },
    {
      "name": "Whiplash Trap",
      "uuid": "9d5f3c12-4d47-505f-b4b0-4eed30a49030",
      "cmc": 5,
      "rarity": "common",
      "color": {
        "colors": [
          "U"
        ],
        "colorIdentity": [
          "U"
        ]
      },
      "type": {
        "types": [
          "Instant"
        ],
        "subtypes": [
          "Trap"
        ],
        "supertypes": []
      }
    },
    {
      "name": "Willbender",
      "uuid": "0ef2b043-3616-53a6-8071-b86c56b3adec",
      "cmc": 2,
      "rarity": "uncommon",
      "color": {
        "colors": [
          "U"
        ],
        "colorIdentity": [
          "U"
        ]
      },
      "type": {
        "types": [
          "Creature"
        ],
        "subtypes": [
          "Human",
          "Wizard"
        ],
        "supertypes": []
      }
    },
    {
      "name": "Zurgo Helmsmasher",
      "uuid": "95affd9d-36c6-521b-a44a-09975c2c1a6d",
      "cmc": 5,
      "rarity": "mythic",
      "color": {
        "colors": [
          "B",
          "R",
          "W"
        ],
        "colorIdentity": [
          "B",
          "R",
          "W"
        ]
      },
      "type": {
        "types": [
          "Creature"
        ],
        "subtypes": [
          "Orc",
          "Warrior"
        ],
        "supertypes": [
          "Legendary"
        ]
      }
    }
  ]
}
