{
  "booster": null,
  "name": "Friday Night Magic 2004",
  "code": "F04",
  "totalSetSize": 12,
  "cards": [
    {
      "name": "Accumulated Knowledge",
      "uuid": "db3d04df-e602-5eec-a4ec-9cc5c3f0d167",
      "cmc": 2,
      "rarity": "rare",
      "color": {
        "colors": [
          "U"
        ],
        "colorIdentity": [
          "U"
        ]
      },
      "type": {
        "types": [
          "Instant"
        ],
        "subtypes": [],
        "supertypes": []
      }
    },
    {
      "name": "Avalanche Riders",
      "uuid": "53fb452f-7b72-57cf-9246-ed9bf8dbc773",
      "cmc": 4,
      "rarity": "rare",
      "color": {
        "colors": [
          "R"
        ],
        "colorIdentity": [
          "R"
        ]
      },
      "type": {
        "types": [
          "Creature"
        ],
        "subtypes": [
          "Human",
          "Nomad"
        ],
        "supertypes": []
      }
    },
    {
      "name": "Brainstorm",
      "uuid": "d39164a8-cac3-59b7-b8dd-e59925251eb8",
      "cmc": 1,
      "rarity": "rare",
      "color": {
        "colors": [
          "U"
        ],
        "colorIdentity": [
          "U"
        ]
      },
      "type": {
        "types": [
          "Instant"
        ],
        "subtypes": [],
        "supertypes": []
      }
    },
    {
      "name": "Carrion Feeder",
      "uuid": "5cf396df-b7e3-52a8-a077-140d277b4f67",
      "cmc": 1,
      "rarity": "rare",
      "color": {
        "colors": [
          "B"
        ],
        "colorIdentity": [
          "B"
        ]
      },
      "type": {
        "types": [
          "Creature"
        ],
        "subtypes": [
          "Zombie"
        ],
        "supertypes": []
      }
    },
    {
      "name": "Krosan Warchief",
      "uuid": "e19eda78-9f8a-5e38-bb4b-8e6a2a39a626",
      "cmc": 3,
      "rarity": "rare",
      "color": {
        "colors": [
          "G"
        ],
        "colorIdentity": [
          "G"
        ]
      },
      "type": {
        "types": [
          "Creature"
        ],
        "subtypes": [
          "Beast"
        ],
        "supertypes": []
      }
    },
    {
      "name": "Lightning Rift",
      "uuid": "ba4730c9-1afe-570c-8fc1-4c49c63a3728",
      "cmc": 2,
      "rarity": "rare",
      "color": {
        "colors": [
          "R"
        ],
        "colorIdentity": [
          "R"
        ]
      },
      "type": {
        "types": [
          "Enchantment"
        ],
        "subtypes": [],
        "supertypes": []
      }
    },
    {
      "name": "Mother of Runes",
      "uuid": "64b14876-f49b-5c6a-a5b1-d95218231663",
      "cmc": 1,
      "rarity": "rare",
      "color": {
        "colors": [
          "W"
        ],
        "colorIdentity": [
          "W"
        ]
      },
      "type": {
        "types": [
          "Creature"
        ],
        "subtypes": [
          "Human",
          "Cleric"
        ],
        "supertypes": []
      }
    },
    {
      "name": "Reanimate",
      "uuid": "600aac96-0ac9-5ad2-b085-2b67340a77b6",
      "cmc": 1,
      "rarity": "rare",
      "color": {
        "colors": [
          "B"
        ],
        "colorIdentity": [
          "B"
        ]
      },
      "type": {
        "types": [
          "Sorcery"
        ],
        "subtypes": [],
        "supertypes": []
      }
    },
    {
      "name": "Silver Knight",
      "uuid": "19a219e1-079a-58e4-b121-74e8f49dd4b5",
      "cmc": 2,
      "rarity": "rare",
      "color": {
        "colors": [
          "W"
        ],
        "colorIdentity": [
          "W"
        ]
      },
      "type": {
        "types": [
          "Creature"
        ],
        "subtypes": [
          "Human",
          "Knight"
        ],
        "supertypes": []
      }
    },
    {
      "name": "Slice and Dice",
      "uuid": "e433614e-8c9c-536e-9b70-277550d48292",
      "cmc": 6,
      "rarity": "rare",
      "color": {
        "colors": [
          "R"
        ],
        "colorIdentity": [
          "R"
        ]
      },
      "type": {
        "types": [
          "Sorcery"
        ],
        "subtypes": [],
        "supertypes": []
      }
    },
    {
      "name": "Treetop Village",
      "uuid": "329efdf8-6597-5fab-82d5-726677c5ebaf",
      "cmc": 0,
      "rarity": "rare",
      "color": {
        "colors": [],
        "colorIdentity": [
          "G"
        ]
      },
      "type": {
        "types": [
          "Land"
        ],
        "subtypes": [],
        "supertypes": []
      }
    },
    {
      "name": "Willbender",
      "uuid": "c30d6569-c77e-5057-bcb4-7f7181c5ac8f",
      "cmc": 2,
      "rarity": "rare",
      "color": {
        "colors": [
          "U"
        ],
        "colorIdentity": [
          "U"
        ]
      },
      "type": {
        "types": [
          "Creature"
        ],
        "subtypes": [
          "Human",
          "Wizard"
        ],
        "supertypes": []
      }
    }
  ]
}
