{
  "booster": null,
  "name": "Judge Gift Cards 2005",
  "code": "G05",
  "totalSetSize": 4,
  "cards": [
    {
      "name": "Gemstone Mine",
      "uuid": "d05e330d-1cb5-572b-9adb-b020fd7a5d49",
      "cmc": 0,
      "rarity": "rare",
      "color": {
        "colors": [],
        "colorIdentity": []
      },
      "type": {
        "types": [
          "Land"
        ],
        "subtypes": [],
        "supertypes": []
      }
    },
    {
      "name": "Mishra's Factory",
      "uuid": "e3cd33f9-5ea1-50c9-a7b3-34db35c5f92e",
      "cmc": 0,
      "rarity": "rare",
      "color": {
        "colors": [],
        "colorIdentity": []
      },
      "type": {
        "types": [
          "Land"
        ],
        "subtypes": [],
        "supertypes": []
      }
    },
    {
      "name": "Regrowth",
      "uuid": "40924b4c-6bb4-5490-bb3c-967cc2a6f87c",
      "cmc": 2,
      "rarity": "rare",
      "color": {
        "colors": [
          "G"
        ],
        "colorIdentity": [
          "G"
        ]
      },
      "type": {
        "types": [
          "Sorcery"
        ],
        "subtypes": [],
        "supertypes": []
      }
    },
    {
      "name": "Sol Ring",
      "uuid": "c0c7dde8-424e-508d-9ada-5d26350da913",
      "cmc": 1,
      "rarity": "rare",
      "color": {
        "colors": [],
        "colorIdentity": []
      },
      "type": {
        "types": [
          "Artifact"
        ],
        "subtypes": [],
        "supertypes": []
      }
    }
  ]
}
